telegram_bot/__init__.py
telegram_bot/command_handler.py
telegram_bot/models/__init__.py
telegram_bot/models/message.py
telegram_bot/models/update.py
telegram_bot/models/user.py
telegram_bot/telegram_bot.py
ab_telegram_bot-1.0.1.dist-info/WHEEL
ab_telegram_bot-1.0.1.dist-info/METADATA
ab_telegram_bot-1.0.1.dist-info/RECORD
